invenio_jsonschemas/__init__.py
invenio_jsonschemas/config.py
invenio_jsonschemas/errors.py
invenio_jsonschemas/ext.py
invenio_jsonschemas/jsonresolver.py
invenio_jsonschemas/proxies.py
invenio_jsonschemas/utils.py
invenio_jsonschemas/views.py
invenio_jsonschemas-2.1.0.dist-info/licenses/AUTHORS.rst
invenio_jsonschemas-2.1.0.dist-info/licenses/LICENSE
invenio_jsonschemas-2.1.0.dist-info/METADATA
invenio_jsonschemas-2.1.0.dist-info/WHEEL
invenio_jsonschemas-2.1.0.dist-info/entry_points.txt
invenio_jsonschemas-2.1.0.dist-info/top_level.txt
invenio_jsonschemas-2.1.0.dist-info/RECORD
