Metadata-Version: 2.4
Name: invenio-jsonschemas
Version: 2.1.0
Summary: "Invenio module for building and serving JSONSchemas."
Home-page: https://github.com/inveniosoftware/invenio-jsonschemas
Author: CERN
Author-email: info@inveniosoftware.org
License: MIT
Keywords: invenio json schema jsonschema
Platform: any
Classifier: Development Status :: 5 - Production/Stable
Requires-Python: >=3.7
License-File: LICENSE
License-File: AUTHORS.rst
Requires-Dist: invenio-base<3.0.0,>=2.3.0
Requires-Dist: jsonref>=0.1
Provides-Extra: tests
Requires-Dist: pytest-black-ng>=0.4.0; extra == "tests"
Requires-Dist: jsonresolver[jsonschema]>=0.2.1; extra == "tests"
Requires-Dist: mock>=1.3.0; extra == "tests"
Requires-Dist: pytest-invenio<4.0.0,>=3.0.0; extra == "tests"
Requires-Dist: sphinx>=4.5; extra == "tests"
Provides-Extra: docs
Dynamic: license-file
